aiomoto/__init__.py
aiomoto/__version__.py
aiomoto/context.py
aiomoto/exceptions.py
aiomoto/patches/__init__.py
aiomoto/patches/core.py
aiomoto/patches/server_mode.py
aiomoto/py.typed
aiomoto-0.3.0.dist-info/WHEEL
aiomoto-0.3.0.dist-info/METADATA
aiomoto-0.3.0.dist-info/RECORD
